{
  "type": "minecraft:crafting_shapeless",
  "ingredients": [
    {
      "tag": "clay:soldiers"
    },
    {
      "tag": "clay:soldiers"
    },
    {
      "tag": "clay:soldiers"
    },
    {
      "tag": "clay:soldiers"
    },
    {
      "tag": "clay:soldiers"
    },
    {
      "tag": "clay:soldiers"
    },
    {
      "tag": "clay:soldiers"
    },
    {
      "tag": "clay:soldiers"
    },
    {
      "item": "minecraft:gray_dye"
    }
  ],
  "result": {
    "count": 8,
    "id": "clay:soldier/gray"
  }
}